framework_favicon/__init__.py
framework_favicon/database.py
framework_favicon/framework_hash.py
framework_favicon/grab_result.py
framework_favicon/grabbers.py
framework_favicon/main.py
framework_favicon/utils.py
framework_favicon/values.py
tests/__init__.py
tests/test_base.py
tests/test_cli.py
tests/test_grabbers.py
tests/values.py
framework_favicon-0.1.dist-info/LICENSE
framework_favicon-0.1.dist-info/METADATA
framework_favicon-0.1.dist-info/WHEEL
framework_favicon-0.1.dist-info/entry_points.txt
framework_favicon-0.1.dist-info/top_level.txt
framework_favicon-0.1.dist-info/RECORD
