Metadata-Version: 2.1
Name: framework-favicon
Version: 0.1
Summary: framework guessing from favicon
Home-page: https://github.com/sensokame/framework-from-favicon
Author: sensokame
Author-email: justhoucem@gmail.com
License: MIT
Keywords: automation,testing,systems,devices
Classifier: License :: OSI Approved :: MIT No Attribution License (MIT-0)
Classifier: Programming Language :: Python :: 3
Classifier: Programming Language :: Python :: 3.10
Requires-Python: >=3.6
License-File: LICENSE
Requires-Dist: beautifulsoup4
Requires-Dist: rich
Requires-Dist: argparse
Requires-Dist: validators
Requires-Dist: unittest-xml-reporting
Provides-Extra: dev
Requires-Dist: pdoc3 ; extra == 'dev'
Requires-Dist: flake8 ; extra == 'dev'
Requires-Dist: twine ; extra == 'dev'
Requires-Dist: setuptools ; extra == 'dev'
Requires-Dist: autopep8 ; extra == 'dev'
